authstats/__init__.py
authstats/admin.py
authstats/api.py
authstats/app_settings.py
authstats/apps.py
authstats/auth_hooks.py
authstats/managers.py
authstats/models.py
authstats/providers.py
authstats/schema.py
authstats/signals.py
authstats/tasks.py
authstats/urls.py
authstats/utils.py
authstats/validators.py
authstats/views.py
authstats/locale/en/LC_MESSAGES/django.po
authstats/management/commands/__init.py
authstats/management/commands/reports_bootstrap_report.py
authstats/management/commands/reports_refresh_all_reports.py
authstats/management/commands/reports_run_report.py
authstats/management/commands/reports_sync_filters.py
authstats/migrations/0001_initial.py
authstats/migrations/0002_reportdatathrough_checkbox_only.py
authstats/migrations/0003_authreportsconfiguration_states_to_include.py
authstats/migrations/0004_alter_authreportsconfiguration_options.py
authstats/migrations/0005_alter_authreportsconfiguration_options_and_more.py
authstats/migrations/0006_report_show_character_image.py
authstats/migrations/0007_reportdatathrough_allow_sort.py
authstats/migrations/0008_alter_reportdatathrough_long_descriptions.py
authstats/migrations/__init__.py
authstats/static/authstats/bs3/manifest.json
authstats/static/authstats/bs3/assets/@libs-3ucQeUj1.js
authstats/static/authstats/bs3/assets/@libs-3ucQeUj1.js.map
authstats/static/authstats/bs3/assets/@react-router-DHoxyQNO.js
authstats/static/authstats/bs3/assets/@react-router-DHoxyQNO.js.map
authstats/static/authstats/bs3/assets/index-CCQS2-LS.css
authstats/static/authstats/bs3/assets/index-D0eV-U1d.js
authstats/static/authstats/bs3/assets/index-D0eV-U1d.js.map
authstats/static/authstats/bs5/manifest.json
authstats/static/authstats/bs5/assets/@libs-HR9CGimh.js
authstats/static/authstats/bs5/assets/@libs-HR9CGimh.js.map
authstats/static/authstats/bs5/assets/@react-router-DGPw9KQn.js
authstats/static/authstats/bs5/assets/@react-router-DGPw9KQn.js.map
authstats/static/authstats/bs5/assets/index-CyKVLMpI.js
allianceauth_auth_stats-0.1.1.dist-info/licenses/LICENSE
allianceauth_auth_stats-0.1.1.dist-info/WHEEL
allianceauth_auth_stats-0.1.1.dist-info/METADATA
allianceauth_auth_stats-0.1.1.dist-info/RECORD
